{"id":890,"slug":"13-055SR08-marseille-secteur-8","nom_standard":"Marseille Secteur 8","code_postal":"13","code_departement":"13","libelle_departement":"Bouches-du-Rhône","code_commune":"055SR08","Tour 1":{"Inscrits":47721,"Abstentions":34692,"% Abs/Ins":72.7,"Votants":13029,"% Vot/Ins":27.3,"Blancs":120,"% Blancs/Ins":0.25,"% Blancs/Vot":0.92,"Nuls":237,"% Nuls/Ins":0.5,"% Nuls/Vot":1.82,"Exprimés":12672,"% Exp/Ins":26.55,"% Exp/Vot":97.26,"resultats":[{"N.Pan.":null,"Code Nuance":"LDVG","Sexe":"F","Nom":"GHALI","Prénom":"Samia","Liste":"MARSEILLE AVANT TOUT AVEC SAMIA GHALI","Sièges / Elu":"0","Sièges Secteur":0,"Sièges CC":0,"Voix":3275,"% Voix/Ins":6.86,"% Voix/Exp":25.84},{"N.Pan.":2,"Code Nuance":"LLR","Sexe":"M","Nom":"MAASKRI","Prénom":"Moussa","Liste":"Une volonté pour Marseille avec Martine VASSAL","Sièges / Elu":"0","Sièges Secteur":0,"Sièges CC":0,"Voix":1736,"% Voix/Ins":3.64,"% Voix/Exp":13.7},{"N.Pan.":3,"Code Nuance":"LEXG","Sexe":"M","Nom":"ROCHE","Prénom":"François","Liste":"Lutte ouvrière - Faire entendre le camp des travailleurs","Sièges / Elu":0,"Sièges CC":0,"Voix":125,"% Voix/Ins":0.26,"% Voix/Exp":0.99},{"N.Pan.":4,"Code Nuance":"LRN","Sexe":"F","Nom":"GRECH","Prénom":"Sophie","Liste":"AVEC STEPHANE RAVIER, RETROUVONS MARSEILLE !","Sièges / Elu":0,"Sièges CC":0,"Voix":2810,"% Voix/Ins":5.89,"% Voix/Exp":22.17},{"N.Pan.":5,"Code Nuance":"LUG","Sexe":"M","Nom":"COPPOLA","Prénom":"Jean-Marc","Liste":"LE PRINTEMPS MARSEILLAIS, LE RASSEMBLEMENT DE LA GAUCHE, DES ECOLOGISTES ET DES CITOYENS","Sièges / Elu":0,"Sièges CC":0,"Voix":2428,"% Voix/Ins":5.09,"% Voix/Exp":19.16},{"N.Pan.":6,"Code Nuance":"LDVD","Sexe":"M","Nom":"CORTEGGIANI","Prénom":"Jean-Marc","Liste":"ENSEMBLE POUR MARSEILLE AVEC BRUNO GILLES","Sièges / Elu":0,"Sièges CC":0,"Voix":549,"% Voix/Ins":1.15,"% Voix/Exp":4.33},{"N.Pan.":7,"Code Nuance":"LEXG","Sexe":"M","Nom":"PERNICE","Prénom":"Stephane","Liste":"liste ouvrière d'unité soutenue par le POID : \"Marseille : retour aux services publics","Sièges / Elu":0,"Sièges CC":0,"Voix":57,"% Voix/Ins":0.12,"% Voix/Exp":0.45},{"N.Pan.":8,"Code Nuance":"LREM","Sexe":"M","Nom":"AHAMADA","Prénom":"Saïd","Liste":"BERLAND 2020","Sièges / Elu":0,"Sièges CC":0,"Voix":1008,"% Voix/Ins":2.11,"% Voix/Exp":7.95},{"N.Pan.":9,"Code Nuance":"LVEC","Sexe":"F","Nom":"SOILIHI","Prénom":"Chahidati","Liste":"DEBOUT MARSEILLE","Sièges / Elu":0,"Sièges CC":0,"Voix":684,"% Voix/Ins":1.43,"% Voix/Exp":5.4}]},"Tour 2":{"Inscrits":47912,"Abstentions":34356,"% Abs/Ins":71.71,"Votants":13556,"% Vot/Ins":28.29,"Blancs":266,"% Blancs/Ins":0.56,"% Blancs/Vot":1.96,"Nuls":125,"% Nuls/Ins":0.26,"% Nuls/Vot":0.92,"Exprimés":13165,"% Exp/Ins":27.48,"% Exp/Vot":97.12,"resultats":[{"N.Pan.":1,"Code Nuance":"LDVG","Sexe":"F","Nom":"GHALI","Prénom":"Samia","Liste":"TOUS UNIS AVEC SAMIA GHALI","Sièges / Elu":8,"Sièges Secteur":17,"Sièges CC":8,"Voix":5025,"% Voix/Ins":10.49,"% Voix/Exp":38.17},{"N.Pan.":4,"Code Nuance":"LRN","Sexe":"F","Nom":"GRECH","Prénom":"Sophie","Liste":"AVEC STEPHANE RAVIER, RETROUVONS MARSEILLE !","Sièges / Elu":2,"Sièges Secteur":3,"Sièges CC":1,"Voix":3501,"% Voix/Ins":7.31,"% Voix/Exp":26.59},{"N.Pan.":5,"Code Nuance":"LUG","Sexe":"M","Nom":"COPPOLA","Prénom":"Jean-Marc","Liste":"LE PRINTEMPS MARSEILLAIS, LE RASSEMBLEMENT DE LA GAUCHE, DES ECOLOGISTES ET DES CITOYENS","Sièges / Elu":2,"Sièges Secteur":4,"Sièges CC":2,"Voix":4639,"% Voix/Ins":9.68,"% Voix/Exp":35.24}]},"population":{"F0-2":2163.539439275753,"F3-5":2293.744322043734,"F6-10":3669.790000172357,"F11-17":4761.223531863742,"F18-24":4345.604890007255,"F25-39":9612.01856609594,"F40-54":9304.59295984107,"F55-64":5253.10424945279,"F65-79":5225.24531689042,"F80+":2489.0691403226683,"H0-2":2316.445028502563,"H3-5":2338.36543558249,"H6-10":3895.960635465165,"H11-17":5045.918095409157,"H18-24":4380.454868243502,"H25-39":8192.71169732331,"H40-54":8660.308614633741,"H55-64":5026.30503510579,"H65-79":4523.693050891282,"H80+":1602.905122877244},"Analyse":{"Votes décisifs":386,"tour décisif":2,"majeurs":68616.013511685,"Non votants de 18-24":7002.111367359425}}