{"id":951,"slug":"14-6-amaye-sur-orne","nom_standard":"Amayé-sur-Orne","code_postal":"14","code_departement":"14","libelle_departement":"Calvados","code_commune":"6","Tour 1":{"Inscrits":756,"Abstentions":281,"% Abs/Ins":37.17,"Votants":475,"% Vot/Ins":62.83,"Blancs":11,"% Blancs/Ins":1.46,"% Blancs/Vot":2.32,"Nuls":4,"% Nuls/Ins":0.53,"% Nuls/Vot":0.84,"Exprimés":460,"% Exp/Ins":60.85,"% Exp/Vot":96.84,"resultats":[{"N.Pan.":null,"Code Nuance":"LNC","Sexe":"F","Nom":"DELAUNAY","Prénom":"Martine","Liste":"AMAYÉ 2020 : POUR VOUS, AVEC NOUS","Sièges / Elu":"3","Sièges Secteur":0,"Sièges CC":0,"Voix":207,"% Voix/Ins":27.38,"% Voix/Exp":45},{"N.Pan.":2,"Code Nuance":"LNC","Sexe":"M","Nom":"COLINO","Prénom":"Sylvain","Liste":"VERS UNE NOUVELLE DYNAMIQUE","Sièges / Elu":"12","Sièges Secteur":0,"Sièges CC":1,"Voix":253,"% Voix/Ins":33.47,"% Voix/Exp":55}]},"population":{"F0-2":14.3519095587605,"F3-5":10.9949207590046,"F6-10":36.4318447569095,"F11-17":72.5825384695529,"F18-24":25.2082794977228,"F25-39":77.7086378546331,"F40-54":129.707180608766,"F55-64":68.7370682911099,"F65-79":93.9693090524967,"F80+":22.5822700310939,"H0-2":19.7510442043055,"H3-5":17.0622107488039,"H6-10":31.5219270435604,"H11-17":66.3393814846122,"H18-24":20.9162059488931,"H25-39":72.5847823804768,"H40-54":127.576731876302,"H55-64":53.6030301784296,"H65-79":89.8919938964695,"H80+":15.4787333580975},"Analyse":{"Votes décisifs":47,"tour décisif":1,"majeurs":797.9642229744909,"Non votants de 18-24":18.668203628022468}}