{"id":2223,"slug":"28-173-gasville-oiseme","nom_standard":"Gasville-Oisème","code_postal":"28","code_departement":"28","libelle_departement":"Eure-et-Loir","code_commune":"173","Tour 1":{"Inscrits":1012,"Abstentions":405,"% Abs/Ins":40.02,"Votants":607,"% Vot/Ins":59.98,"Blancs":7,"% Blancs/Ins":0.69,"% Blancs/Vot":1.15,"Nuls":2,"% Nuls/Ins":0.2,"% Nuls/Vot":0.33,"Exprimés":598,"% Exp/Ins":59.09,"% Exp/Vot":98.52,"resultats":[{"N.Pan.":null,"Code Nuance":"LNC","Sexe":"M","Nom":"ROUAULT","Prénom":"Romain","Liste":"Pour Gasville-Oisème : Protégeons notre environnement et améliorons notre cadre de vie","Sièges / Elu":"12","Sièges Secteur":0,"Sièges CC":1,"Voix":327,"% Voix/Ins":32.31,"% Voix/Exp":54.68},{"N.Pan.":2,"Code Nuance":"LNC","Sexe":"M","Nom":"HOYAU","Prénom":"Jérôme","Liste":"Un nouvel élan pour notre commune","Sièges / Elu":"3","Sièges Secteur":0,"Sièges CC":0,"Voix":271,"% Voix/Ins":26.78,"% Voix/Exp":45.32}]},"population":{"F0-2":23.9667312844111,"F3-5":26.9146776090433,"F6-10":51.4024910916752,"F11-17":54.5918911016574,"F18-24":23.5745926621224,"F25-39":131.983193616308,"F40-54":153.672534569765,"F55-64":91.2399563511753,"F65-79":115.759824245021,"F80+":71.5347373885349,"H0-2":33.0800457728698,"H3-5":27.2144677054055,"H6-10":46.4963029292223,"H11-17":66.8073568879033,"H18-24":32.8440625125124,"H25-39":112.18742362443,"H40-54":172.929091628732,"H55-64":83.5557202479783,"H65-79":121.831795466451,"H80+":47.4131033047815},"Analyse":{"Votes décisifs":57,"tour décisif":1,"majeurs":1158.526035617812,"Non votants de 18-24":26.858573969605388}}