{"id":2746,"slug":"31-547-seysses","nom_standard":"Seysses","code_postal":"31","code_departement":"31","libelle_departement":"Haute-Garonne","code_commune":"547","Tour 1":{"Inscrits":5777,"Abstentions":3550,"% Abs/Ins":61.45,"Votants":2227,"% Vot/Ins":38.55,"Blancs":30,"% Blancs/Ins":0.52,"% Blancs/Vot":1.35,"Nuls":41,"% Nuls/Ins":0.71,"% Nuls/Vot":1.84,"Exprimés":2156,"% Exp/Ins":37.32,"% Exp/Vot":96.81,"resultats":[{"N.Pan.":null,"Code Nuance":"LDVC","Sexe":"F","Nom":"VALLIER","Prénom":"Vicky","Liste":"AGIR SDR","Sièges / Elu":"7","Sièges Secteur":0,"Sièges CC":1,"Voix":1008,"% Voix/Ins":17.45,"% Voix/Exp":46.75},{"N.Pan.":2,"Code Nuance":"LDVG","Sexe":"M","Nom":"BOUTELOUP","Prénom":"Jérôme","Liste":"SEYSSES ENSEMBLE","Sièges / Elu":"22","Sièges Secteur":0,"Sièges CC":3,"Voix":1148,"% Voix/Ins":19.87,"% Voix/Exp":53.25}]},"population":{"F0-2":163.985029773691,"F3-5":163.295310917954,"F6-10":285.390981987102,"F11-17":360.785285148718,"F18-24":289.671688734228,"F25-39":891.729259387091,"F40-54":1085.39139705333,"F55-64":520.772081338305,"F65-79":529.594793801299,"F80+":222.936019681478,"H0-2":131.490548626834,"H3-5":174.901631832499,"H6-10":263.541696114373,"H11-17":387.6173120623,"H18-24":580.507255633953,"H25-39":1379.94410341852,"H40-54":1087.29931234796,"H55-64":515.493889396654,"H65-79":527.330666647386,"H80+":163.321736096329},"Analyse":{"Votes décisifs":141,"tour décisif":1,"majeurs":7793.992203536533,"Non votants de 18-24":621.5401905048375}}