{"id":289,"slug":"3-94-creuzier-le-vieux","nom_standard":"Creuzier-le-Vieux","code_postal":"3","code_departement":"3","libelle_departement":"Allier","code_commune":"94","Tour 1":{"Inscrits":2845,"Abstentions":1351,"% Abs/Ins":47.49,"Votants":1494,"% Vot/Ins":52.51,"Blancs":14,"% Blancs/Ins":0.49,"% Blancs/Vot":0.94,"Nuls":14,"% Nuls/Ins":0.49,"% Nuls/Vot":0.94,"Exprimés":1466,"% Exp/Ins":51.53,"% Exp/Vot":98.13,"resultats":[{"N.Pan.":null,"Code Nuance":"LNC","Sexe":"M","Nom":"FAYET","Prénom":"Hadrien","Liste":"Ensemble pour l'Avenir de Creuzier-le-Vieux","Sièges / Elu":"18","Sièges Secteur":0,"Sièges CC":2,"Voix":751,"% Voix/Ins":26.4,"% Voix/Exp":51.23},{"N.Pan.":2,"Code Nuance":"LNC","Sexe":"M","Nom":"BERTIN","Prénom":"Christian","Liste":"Pour vous, Avec vous construisons demain","Sièges / Elu":"5","Sièges Secteur":0,"Sièges CC":0,"Voix":715,"% Voix/Ins":25.13,"% Voix/Exp":48.77}]},"population":{"F0-2":38.3087637942606,"F3-5":47.9968000568789,"F6-10":75.4229747587208,"F11-17":132.424808635619,"F18-24":58.4140114966875,"F25-39":223.342475516016,"F40-54":355.656178738489,"F55-64":306.489433971972,"F65-79":337.459759720955,"F80+":96.0907299920937,"H0-2":34.3550188126101,"H3-5":39.1929629259522,"H6-10":83.256560670133,"H11-17":139.35971586802,"H18-24":91.883918768008,"H25-39":209.134268909942,"H40-54":303.496367570648,"H55-64":286.951902557358,"H65-79":344.177504645982,"H80+":79.5858425896549},"Analyse":{"Votes décisifs":37,"tour décisif":1,"majeurs":2692.682394477806,"Non votants de 18-24":66.90706757849249}}