{"id":2304,"slug":"29-40-le-conquet","nom_standard":"Le Conquet","code_postal":"29","code_departement":"29","libelle_departement":"Finistère","code_commune":"40","Tour 1":{"Inscrits":2413,"Abstentions":892,"% Abs/Ins":36.97,"Votants":1521,"% Vot/Ins":63.03,"Blancs":20,"% Blancs/Ins":0.83,"% Blancs/Vot":1.31,"Nuls":17,"% Nuls/Ins":0.7,"% Nuls/Vot":1.12,"Exprimés":1484,"% Exp/Ins":61.5,"% Exp/Vot":97.57,"resultats":[{"N.Pan.":null,"Code Nuance":"LNC","Sexe":"M","Nom":"MILIN","Prénom":"Jean-Luc","Liste":"LE CONQUET NOUS RASSEMBLE","Sièges / Elu":"18","Sièges Secteur":0,"Sièges CC":2,"Voix":855,"% Voix/Ins":35.43,"% Voix/Exp":57.61},{"N.Pan.":2,"Code Nuance":"LNC","Sexe":"F","Nom":"STORCK","Prénom":"Christiane","Liste":"ENERGIE NOUVELLE POUR LE CONQUET","Sièges / Elu":"5","Sièges Secteur":0,"Sièges CC":1,"Voix":629,"% Voix/Ins":26.07,"% Voix/Exp":42.39}]},"population":{"F0-2":22,"F3-5":43,"F6-10":75,"F11-17":92,"F18-24":54,"F25-39":145,"F40-54":251,"F55-64":264,"F65-79":335,"F80+":196,"H0-2":24,"H3-5":23,"H6-10":70,"H11-17":87,"H18-24":63,"H25-39":132,"H40-54":223,"H55-64":245,"H65-79":319,"H80+":105},"Analyse":{"Votes décisifs":227,"tour décisif":1,"majeurs":2332,"Non votants de 18-24":40.68910806174958}}