{"id":3373,"slug":"35-288-saint-malo","nom_standard":"Saint-Malo","code_postal":"35","code_departement":"35","libelle_departement":"Ille-et-Vilaine","code_commune":"288","Tour 1":{"Inscrits":38060,"Abstentions":20946,"% Abs/Ins":55.03,"Votants":17114,"% Vot/Ins":44.97,"Blancs":83,"% Blancs/Ins":0.22,"% Blancs/Vot":0.48,"Nuls":244,"% Nuls/Ins":0.64,"% Nuls/Vot":1.43,"Exprimés":16787,"% Exp/Ins":44.11,"% Exp/Vot":98.09,"resultats":[{"N.Pan.":null,"Code Nuance":"LUG","Sexe":"F","Nom":"BOURQUARD","Prénom":"Christine","Liste":"SAINT MALO CITE VERTE ET SOLIDAIRE","Sièges / Elu":"0","Sièges Secteur":0,"Sièges CC":0,"Voix":1344,"% Voix/Ins":3.53,"% Voix/Exp":8.01},{"N.Pan.":2,"Code Nuance":"LRN","Sexe":"M","Nom":"MIAILHES","Prénom":"Philippe","Liste":"RASSEMBLEMENT POUR SAINT MALO","Sièges / Elu":"0","Sièges Secteur":0,"Sièges CC":0,"Voix":683,"% Voix/Ins":1.79,"% Voix/Exp":4.07},{"N.Pan.":3,"Code Nuance":"LDVD","Sexe":"M","Nom":"COUDRAY","Prénom":"Jean","Liste":"TOUS MALOUINS","Sièges / Elu":0,"Sièges CC":0,"Voix":1506,"% Voix/Ins":3.96,"% Voix/Exp":8.97},{"N.Pan.":4,"Code Nuance":"LDVC","Sexe":"F","Nom":"LE GAGNE","Prénom":"Anne","Liste":"SAINT-MALO AU COEUR DES POSSIBLES","Sièges / Elu":0,"Sièges CC":0,"Voix":2230,"% Voix/Ins":5.86,"% Voix/Exp":13.28},{"N.Pan.":5,"Code Nuance":"LDVC","Sexe":"M","Nom":"PERRIN","Prénom":"Stéphane","Liste":"SAINT MALO C'EST VOUS!","Sièges / Elu":0,"Sièges CC":0,"Voix":1677,"% Voix/Ins":4.41,"% Voix/Exp":9.99},{"N.Pan.":6,"Code Nuance":"LDVG","Sexe":"M","Nom":"GUILLARD","Prénom":"Alain","Liste":"SAINT-MALO AUTREMENT","Sièges / Elu":0,"Sièges CC":0,"Voix":1387,"% Voix/Ins":3.64,"% Voix/Exp":8.26},{"N.Pan.":7,"Code Nuance":"LDVD","Sexe":"M","Nom":"LURTON","Prénom":"Gilles","Liste":"Saint-Malo Notre lien","Sièges / Elu":0,"Sièges CC":0,"Voix":7960,"% Voix/Ins":20.91,"% Voix/Exp":47.42}]},"Tour 2":{"Inscrits":38006,"Abstentions":22067,"% Abs/Ins":58.06,"Votants":15939,"% Vot/Ins":41.94,"Blancs":546,"% Blancs/Ins":1.44,"% Blancs/Vot":3.43,"Nuls":293,"% Nuls/Ins":0.77,"% Nuls/Vot":1.84,"Exprimés":15100,"% Exp/Ins":39.73,"% Exp/Vot":94.74,"resultats":[{"N.Pan.":4,"Code Nuance":"LDVC","Sexe":"F","Nom":"LE GAGNE","Prénom":"Anne","Liste":"SAINT-MALO AU COEUR DES POSSIBLES","Sièges / Elu":6,"Sièges Secteur":0,"Sièges CC":4,"Voix":4424,"% Voix/Ins":11.64,"% Voix/Exp":29.3},{"N.Pan.":7,"Code Nuance":"LDVD","Sexe":"M","Nom":"LURTON","Prénom":"Gilles","Liste":"Saint-Malo Notre lien","Sièges / Elu":37,"Sièges Secteur":0,"Sièges CC":26,"Voix":10676,"% Voix/Ins":28.09,"% Voix/Exp":70.7}]},"population":{"F0-2":536.711025412684,"F3-5":547.207597823786,"F6-10":901.72602554564,"F11-17":1529.62721617268,"F18-24":1536.36910246737,"F25-39":3209.2096748416,"F40-54":4383.04208362781,"F55-64":3751.37522007197,"F65-79":5965.71376207064,"F80+":3438.61596668344,"H0-2":527.950251673604,"H3-5":530.48239691457,"H6-10":965.572661428513,"H11-17":1598.60154327024,"H18-24":1818.37185521772,"H25-39":3142.25312145525,"H40-54":3759.06578925742,"H55-64":3005.93392839704,"H65-79":4268.70802257323,"H80+":1578.4627550948},"Analyse":{"Votes décisifs":6252,"tour décisif":2,"majeurs":39857.121281758285,"Non votants de 18-24":2013.168500744623}}