{"id":3127,"slug":"34-198-perols","nom_standard":"Pérols","code_postal":"34","code_departement":"34","libelle_departement":"Hérault","code_commune":"198","Tour 1":{"Inscrits":7785,"Abstentions":3933,"% Abs/Ins":50.52,"Votants":3852,"% Vot/Ins":49.48,"Blancs":33,"% Blancs/Ins":0.42,"% Blancs/Vot":0.86,"Nuls":59,"% Nuls/Ins":0.76,"% Nuls/Vot":1.53,"Exprimés":3760,"% Exp/Ins":48.3,"% Exp/Vot":97.61,"resultats":[{"N.Pan.":null,"Code Nuance":"LDVD","Sexe":"F","Nom":"PROST","Prénom":"Cathy","Liste":"Pérols Démocratie Citoyenne","Sièges / Elu":"0","Sièges Secteur":0,"Sièges CC":0,"Voix":838,"% Voix/Ins":10.76,"% Voix/Exp":22.29},{"N.Pan.":2,"Code Nuance":"LDVD","Sexe":"F","Nom":"GIANIEL","Prénom":"Isabelle","Liste":"UNIR PEROLS","Sièges / Elu":"0","Sièges Secteur":0,"Sièges CC":0,"Voix":1095,"% Voix/Ins":14.07,"% Voix/Exp":29.12},{"N.Pan.":3,"Code Nuance":"LRN","Sexe":"M","Nom":"WASELYNCK","Prénom":"Serge","Liste":"RASSEMBLEMENT POUR PEROLS","Sièges / Elu":0,"Sièges CC":0,"Voix":210,"% Voix/Ins":2.7,"% Voix/Exp":5.59},{"N.Pan.":4,"Code Nuance":"LUDI","Sexe":"M","Nom":"RICO","Prénom":"Jean-Pierre","Liste":"ENSEMBLE POUR PEROLS","Sièges / Elu":0,"Sièges CC":0,"Voix":1617,"% Voix/Ins":20.77,"% Voix/Exp":43.01}]},"Tour 2":{"Inscrits":7794,"Abstentions":3944,"% Abs/Ins":50.6,"Votants":3850,"% Vot/Ins":49.4,"Blancs":44,"% Blancs/Ins":0.56,"% Blancs/Vot":1.14,"Nuls":39,"% Nuls/Ins":0.5,"% Nuls/Vot":1.01,"Exprimés":3767,"% Exp/Ins":48.33,"% Exp/Vot":97.84,"resultats":[{"N.Pan.":1,"Code Nuance":"LDVD","Sexe":"F","Nom":"PROST","Prénom":"Cathy","Liste":"Pérols Démocratie Citoyenne","Sièges / Elu":3,"Sièges Secteur":0,"Sièges CC":0,"Voix":744,"% Voix/Ins":9.55,"% Voix/Exp":19.75},{"N.Pan.":2,"Code Nuance":"LDVD","Sexe":"F","Nom":"GIANIEL","Prénom":"Isabelle","Liste":"UNIR PEROLS","Sièges / Elu":4,"Sièges Secteur":0,"Sièges CC":0,"Voix":1202,"% Voix/Ins":15.42,"% Voix/Exp":31.91},{"N.Pan.":4,"Code Nuance":"LUDI","Sexe":"M","Nom":"RICO","Prénom":"Jean-Pierre","Liste":"ENSEMBLE POUR PEROLS","Sièges / Elu":22,"Sièges Secteur":0,"Sièges CC":2,"Voix":1821,"% Voix/Ins":23.36,"% Voix/Exp":48.34}]},"population":{"F0-2":88.413863403349,"F3-5":119.389485729608,"F6-10":223.189583833218,"F11-17":362.613968983565,"F18-24":356.880467173852,"F25-39":639.887627333948,"F40-54":1087.57370903228,"F55-64":638.493488409345,"F65-79":985.371893011006,"F80+":428.513141967357,"H0-2":116.30256902337,"H3-5":117.266420092783,"H6-10":259.414796468032,"H11-17":387.479054470332,"H18-24":387.14409206527,"H25-39":612.209932078969,"H40-54":891.828625575474,"H55-64":580.469268082332,"H65-79":829.436293394756,"H80+":326.121719871149},"Analyse":{"Votes décisifs":619,"tour décisif":2,"majeurs":7763.930257995738,"Non votants de 18-24":375.07552725617757}}