{"id":3514,"slug":"37-163-nazelles-negron","nom_standard":"Nazelles-Négron","code_postal":"37","code_departement":"37","libelle_departement":"Indre-et-Loire","code_commune":"163","Tour 1":{"Inscrits":3033,"Abstentions":1595,"% Abs/Ins":52.59,"Votants":1438,"% Vot/Ins":47.41,"Blancs":12,"% Blancs/Ins":0.4,"% Blancs/Vot":0.83,"Nuls":30,"% Nuls/Ins":0.99,"% Nuls/Vot":2.09,"Exprimés":1396,"% Exp/Ins":46.03,"% Exp/Vot":97.08,"resultats":[{"N.Pan.":null,"Code Nuance":"LDVG","Sexe":"M","Nom":"AHUIR","Prénom":"Christophe","Liste":"Demain Nazelles-Négron","Sièges / Elu":"4","Sièges Secteur":0,"Sièges CC":1,"Voix":450,"% Voix/Ins":14.84,"% Voix/Exp":32.23},{"N.Pan.":2,"Code Nuance":"LUC","Sexe":"F","Nom":"FOUGERON","Prénom":"Corine","Liste":"NOUS C' VOUS","Sièges / Elu":"2","Sièges Secteur":0,"Sièges CC":0,"Voix":192,"% Voix/Ins":6.33,"% Voix/Exp":13.75},{"N.Pan.":3,"Code Nuance":"LREM","Sexe":"M","Nom":"CHATELLIER","Prénom":"Richard","Liste":"AGIR ENSEMBLE POUR NAZELLES NEGRON","Sièges / Elu":21,"Sièges CC":3,"Voix":754,"% Voix/Ins":24.86,"% Voix/Exp":54.01}]},"population":{"F0-2":39.5850701454765,"F3-5":46.1935267677967,"F6-10":94.2009450894515,"F11-17":137.896145451789,"F18-24":72.0609473390956,"F25-39":258.404354497449,"F40-54":332.151533432887,"F55-64":285.831999257691,"F65-79":367.866030178915,"F80+":184.940003307567,"H0-2":42.8675025678677,"H3-5":56.8760631533345,"H6-10":85.7529858027372,"H11-17":127.467915091951,"H18-24":85.1362805070819,"H25-39":251.823168631277,"H40-54":350.374776601665,"H55-64":262.362266208334,"H65-79":336.899003772285,"H80+":106.309482195349},"Analyse":{"Votes décisifs":113,"tour décisif":1,"majeurs":2894.1598459295965,"Non votants de 18-24":79.09179287487696}}