{"id":4485,"slug":"45-115-courtenay","nom_standard":"Courtenay","code_postal":"45","code_departement":"45","libelle_departement":"Loiret","code_commune":"115","Tour 1":{"Inscrits":2918,"Abstentions":1506,"% Abs/Ins":51.61,"Votants":1412,"% Vot/Ins":48.39,"Blancs":13,"% Blancs/Ins":0.45,"% Blancs/Vot":0.92,"Nuls":22,"% Nuls/Ins":0.75,"% Nuls/Vot":1.56,"Exprimés":1377,"% Exp/Ins":47.19,"% Exp/Vot":97.52,"resultats":[{"N.Pan.":null,"Code Nuance":"LUDI","Sexe":"M","Nom":"FOLLET","Prénom":"Philippe","Liste":"Un nouveau souffle pour Courtenay.","Sièges / Elu":"21","Sièges Secteur":0,"Sièges CC":6,"Voix":694,"% Voix/Ins":23.78,"% Voix/Exp":50.4},{"N.Pan.":2,"Code Nuance":"LDVD","Sexe":"M","Nom":"DUFAY","Prénom":"Daniel","Liste":"COURTENAY AVEC VOUS ET POUR VOUS","Sièges / Elu":"2","Sièges Secteur":0,"Sièges CC":1,"Voix":284,"% Voix/Ins":9.73,"% Voix/Exp":20.62},{"N.Pan.":3,"Code Nuance":"LDVC","Sexe":"M","Nom":"PATARD","Prénom":"Jean-Pascal","Liste":"COURTENAY VIVONS NOTRE VILLE!","Sièges / Elu":4,"Sièges CC":1,"Voix":399,"% Voix/Ins":13.67,"% Voix/Exp":28.98}]},"population":{"F0-2":50,"F3-5":42,"F6-10":111,"F11-17":157,"F18-24":86,"F25-39":263,"F40-54":327,"F55-64":261,"F65-79":480,"F80+":279,"H0-2":50,"H3-5":57,"H6-10":92,"H11-17":157,"H18-24":107,"H25-39":243,"H40-54":299,"H55-64":243,"H65-79":398,"H80+":146},"Analyse":{"Votes décisifs":12,"tour décisif":1,"majeurs":3132,"Non votants de 18-24":105.98978288633461}}