{"id":4966,"slug":"51-559-suippes","nom_standard":"Suippes","code_postal":"51","code_departement":"51","libelle_departement":"Marne","code_commune":"559","Tour 1":{"Inscrits":2146,"Abstentions":1149,"% Abs/Ins":53.54,"Votants":997,"% Vot/Ins":46.46,"Blancs":12,"% Blancs/Ins":0.56,"% Blancs/Vot":1.2,"Nuls":9,"% Nuls/Ins":0.42,"% Nuls/Vot":0.9,"Exprimés":976,"% Exp/Ins":45.48,"% Exp/Vot":97.89,"resultats":[{"N.Pan.":null,"Code Nuance":"LDVD","Sexe":"F","Nom":"MORAND","Prénom":"Valérie","Liste":"Suippes nous ressemble, Suippes nous rassemble","Sièges / Elu":"0","Sièges Secteur":0,"Sièges CC":0,"Voix":265,"% Voix/Ins":12.35,"% Voix/Exp":27.15},{"N.Pan.":2,"Code Nuance":"LDVD","Sexe":"M","Nom":"COLLART","Prénom":"François","Liste":"Avec vous pour Suippes","Sièges / Elu":"0","Sièges Secteur":0,"Sièges CC":0,"Voix":450,"% Voix/Ins":20.97,"% Voix/Exp":46.11},{"N.Pan.":3,"Code Nuance":"LRN","Sexe":"M","Nom":"PHILIPPO","Prénom":"Baptiste","Liste":"Rassembler pour Suippes","Sièges / Elu":0,"Sièges CC":0,"Voix":261,"% Voix/Ins":12.16,"% Voix/Exp":26.74}]},"Tour 2":{"Inscrits":2153,"Abstentions":1280,"% Abs/Ins":59.45,"Votants":873,"% Vot/Ins":40.55,"Blancs":7,"% Blancs/Ins":0.33,"% Blancs/Vot":0.8,"Nuls":11,"% Nuls/Ins":0.51,"% Nuls/Vot":1.26,"Exprimés":855,"% Exp/Ins":39.71,"% Exp/Vot":97.94,"resultats":[{"N.Pan.":1,"Code Nuance":"LDVD","Sexe":"F","Nom":"MORAND","Prénom":"Valérie","Liste":"Suippes nous ressemble, Suippes nous rassemble","Sièges / Elu":3,"Sièges Secteur":0,"Sièges CC":2,"Voix":204,"% Voix/Ins":9.48,"% Voix/Exp":23.86},{"N.Pan.":2,"Code Nuance":"LDVD","Sexe":"M","Nom":"COLLART","Prénom":"François","Liste":"Avec vous pour Suippes","Sièges / Elu":22,"Sièges Secteur":0,"Sièges CC":14,"Voix":482,"% Voix/Ins":22.39,"% Voix/Exp":56.37},{"N.Pan.":3,"Code Nuance":"LRN","Sexe":"M","Nom":"PHILIPPO","Prénom":"Baptiste","Liste":"Rassembler pour Suippes","Sièges / Elu":2,"Sièges Secteur":0,"Sièges CC":1,"Voix":169,"% Voix/Ins":7.85,"% Voix/Exp":19.77}]},"population":{"F0-2":60.3173823253476,"F3-5":80.5767908995734,"F6-10":129.968867832666,"F11-17":177.906839648539,"F18-24":125.175530893101,"F25-39":365.66539564402,"F40-54":284.246383259462,"F55-64":205.16910441888,"F65-79":216.680837218544,"F80+":136.257798632756,"H0-2":71.5193221578087,"H3-5":79.7693911706263,"H6-10":124.30973533726,"H11-17":172.035993621299,"H18-24":377.141040366618,"H25-39":499.471803829229,"H40-54":325.958945421674,"H55-64":193.236304749171,"H65-79":192.642992452305,"H80+":62.9495401211181},"Analyse":{"Votes décisifs":278,"tour décisif":2,"majeurs":2984.5956770068774,"Non votants de 18-24":355.3880039874143}}