{"id":5068,"slug":"53-216-saint-fraimbault-de-prieres","nom_standard":"Saint-Fraimbault-de-Prières","code_postal":"53","code_departement":"53","libelle_departement":"Mayenne","code_commune":"216","Tour 1":{"Inscrits":718,"Abstentions":304,"% Abs/Ins":42.34,"Votants":414,"% Vot/Ins":57.66,"Blancs":8,"% Blancs/Ins":1.11,"% Blancs/Vot":1.93,"Nuls":9,"% Nuls/Ins":1.25,"% Nuls/Vot":2.17,"Exprimés":397,"% Exp/Ins":55.29,"% Exp/Vot":95.89,"resultats":[{"N.Pan.":null,"Code Nuance":"LNC","Sexe":"F","Nom":"ZANDRONIS","Prénom":"Pascale","Liste":"Avec vous, notre village demain","Sièges / Elu":"3","Sièges Secteur":0,"Sièges CC":0,"Voix":180,"% Voix/Ins":25.07,"% Voix/Exp":45.34},{"N.Pan.":2,"Code Nuance":"LNC","Sexe":"M","Nom":"MOUTEL","Prénom":"Thierry","Liste":"Unissons-nous pour le bien être et le dynamisme de notre commune","Sièges / Elu":"12","Sièges Secteur":0,"Sièges CC":1,"Voix":217,"% Voix/Ins":30.22,"% Voix/Exp":54.66}]},"population":{"F0-2":7.5532479144035,"F3-5":21.7800648143031,"F6-10":31.326551935155,"F11-17":54.80483497122,"F18-24":32.4955942007277,"F25-39":87.1346188099713,"F40-54":108.868677829273,"F55-64":67.4353888820766,"F65-79":58.8108210259274,"F80+":31.1136172502556,"H0-2":14.3339098536786,"H3-5":19.848318111937,"H6-10":33.7110102835578,"H11-17":44.8590456641748,"H18-24":30.6379609478196,"H25-39":90.9608441363963,"H40-54":104.934071808606,"H55-64":70.5707358491605,"H65-79":56.3684542498859,"H80+":19.4522314614699},"Analyse":{"Votes décisifs":38,"tour décisif":1,"majeurs":758.7830164515698,"Non votants de 18-24":28.687222976104927}}