{"id":5688,"slug":"59-92-bouchain","nom_standard":"Bouchain","code_postal":"59","code_departement":"59","libelle_departement":"Nord","code_commune":"92","Tour 1":{"Inscrits":3098,"Abstentions":1637,"% Abs/Ins":52.84,"Votants":1461,"% Vot/Ins":47.16,"Blancs":25,"% Blancs/Ins":0.81,"% Blancs/Vot":1.71,"Nuls":30,"% Nuls/Ins":0.97,"% Nuls/Vot":2.05,"Exprimés":1406,"% Exp/Ins":45.38,"% Exp/Vot":96.24,"resultats":[{"N.Pan.":null,"Code Nuance":"LDVG","Sexe":"F","Nom":"MESAGLIO","Prénom":"Aurélie","Liste":"EN ROUTE ET A L ECOUTE POUR BOUCHAIN","Sièges / Elu":"1","Sièges Secteur":0,"Sièges CC":0,"Voix":189,"% Voix/Ins":6.1,"% Voix/Exp":13.44},{"N.Pan.":2,"Code Nuance":"LDVG","Sexe":"M","Nom":"ZIENTEK","Prénom":"Ludovic","Liste":"BOUCHAIN ENSEMBLE CONTINUONS","Sièges / Elu":"22","Sièges Secteur":0,"Sièges CC":2,"Voix":796,"% Voix/Ins":25.69,"% Voix/Exp":56.61},{"N.Pan.":3,"Code Nuance":"LDVD","Sexe":"M","Nom":"CAPRON","Prénom":"Olivier","Liste":"BOUCHAIN RENOUVEAU","Sièges / Elu":4,"Sièges CC":0,"Voix":421,"% Voix/Ins":13.59,"% Voix/Exp":29.94}]},"population":{"F0-2":54.597521060347,"F3-5":65.833731931634,"F6-10":98.5145463929468,"F11-17":167.477951800018,"F18-24":97.5610886324434,"F25-39":316.572449432306,"F40-54":384.161554360886,"F55-64":304.923436572481,"F65-79":340.196621836595,"F80+":206.911612852045,"H0-2":48.4343985361375,"H3-5":71.8064563147137,"H6-10":129.590274352605,"H11-17":166.643543061026,"H18-24":122.400285578435,"H25-39":327.590255442608,"H40-54":389.485740715178,"H55-64":300.719953179751,"H65-79":261.297891609005,"H80+":82.2806863388383},"Analyse":{"Votes décisifs":187,"tour décisif":1,"majeurs":3134.1015765505717,"Non votants de 18-24":117.42367405254792}}