{"id":5562,"slug":"57-634-saulny","nom_standard":"Saulny","code_postal":"57","code_departement":"57","libelle_departement":"Moselle","code_commune":"634","Tour 1":{"Inscrits":1256,"Abstentions":610,"% Abs/Ins":48.57,"Votants":646,"% Vot/Ins":51.43,"Blancs":11,"% Blancs/Ins":0.88,"% Blancs/Vot":1.7,"Nuls":0,"% Nuls/Ins":0,"% Nuls/Vot":0,"Exprimés":635,"% Exp/Ins":50.56,"% Exp/Vot":98.3,"resultats":[{"N.Pan.":null,"Code Nuance":"LNC","Sexe":"F","Nom":"SPORMEYEUR","Prénom":"Nathalie","Liste":"SAULNY C'EST VOUS","Sièges / Elu":"12","Sièges Secteur":0,"Sièges CC":1,"Voix":328,"% Voix/Ins":26.11,"% Voix/Exp":51.65},{"N.Pan.":2,"Code Nuance":"LNC","Sexe":"M","Nom":"LASSALAS","Prénom":"Hervé","Liste":"Ensemble pour Saulny","Sièges / Elu":"3","Sièges Secteur":0,"Sièges CC":0,"Voix":307,"% Voix/Ins":24.44,"% Voix/Exp":48.35}]},"population":{"F0-2":26.9491260339403,"F3-5":18.9290916978151,"F6-10":40.8213443671412,"F11-17":55.7906024028761,"F18-24":45.9661203241565,"F25-39":104.024984769511,"F40-54":170.211706463091,"F55-64":143.10250537775,"F65-79":121.105310720016,"F80+":40.5055140656576,"H0-2":17.9325762602375,"H3-5":20.8840136735961,"H6-10":37.7021410272928,"H11-17":72.652172991525,"H18-24":52.9586282973277,"H25-39":103.198512864992,"H40-54":156.126406468075,"H55-64":134.90650957699,"H65-79":122.005597655116,"H80+":25.2271349628935},"Analyse":{"Votes décisifs":22,"tour décisif":1,"majeurs":1219.338931545576,"Non votants de 18-24":46.51488459091859}}