{"id":5899,"slug":"59-477-provin","nom_standard":"Provin","code_postal":"59","code_departement":"59","libelle_departement":"Nord","code_commune":"477","Tour 1":{"Inscrits":3205,"Abstentions":1850,"% Abs/Ins":57.72,"Votants":1355,"% Vot/Ins":42.28,"Blancs":35,"% Blancs/Ins":1.09,"% Blancs/Vot":2.58,"Nuls":73,"% Nuls/Ins":2.28,"% Nuls/Vot":5.39,"Exprimés":1247,"% Exp/Ins":38.91,"% Exp/Vot":92.03,"resultats":[{"N.Pan.":null,"Code Nuance":"LDVD","Sexe":"M","Nom":"ZBIERSKI","Prénom":"Joffrey","Liste":"J'AIME PROVIN - ACTE 2","Sièges / Elu":"27","Sièges Secteur":0,"Sièges CC":1,"Voix":1247,"% Voix/Ins":38.91,"% Voix/Exp":100}]},"population":{"F0-2":92,"F3-5":107,"F6-10":163,"F11-17":218,"F18-24":170,"F25-39":436,"F40-54":491,"F55-64":235,"F65-79":298,"F80+":115,"H0-2":92,"H3-5":84,"H6-10":171,"H11-17":232,"H18-24":194,"H25-39":404,"H40-54":461,"H55-64":253,"H65-79":228,"H80+":44},"Analyse":{"Votes décisifs":1248,"tour décisif":1,"majeurs":3329,"Non votants de 18-24":215.84139381195556}}