{"id":5870,"slug":"59-416-morbecque","nom_standard":"Morbecque","code_postal":"59","code_departement":"59","libelle_departement":"Nord","code_commune":"416","Tour 1":{"Inscrits":2130,"Abstentions":913,"% Abs/Ins":42.86,"Votants":1217,"% Vot/Ins":57.14,"Blancs":13,"% Blancs/Ins":0.61,"% Blancs/Vot":1.07,"Nuls":20,"% Nuls/Ins":0.94,"% Nuls/Vot":1.64,"Exprimés":1184,"% Exp/Ins":55.59,"% Exp/Vot":97.29,"resultats":[{"N.Pan.":null,"Code Nuance":"LNC","Sexe":"M","Nom":"DARQUES","Prénom":"Jérôme","Liste":"A l'Ecoute et au Service de Tous... Continuons Ensemble","Sièges / Elu":"21","Sièges Secteur":0,"Sièges CC":2,"Voix":946,"% Voix/Ins":44.41,"% Voix/Exp":79.9},{"N.Pan.":2,"Code Nuance":"LNC","Sexe":"M","Nom":"REEBER","Prénom":"Dominique","Liste":"Morbecque Ensemble Autrement","Sièges / Elu":"2","Sièges Secteur":0,"Sièges CC":0,"Voix":238,"% Voix/Ins":11.17,"% Voix/Exp":20.1}]},"population":{"F0-2":28.5230216727067,"F3-5":39.828941551032,"F6-10":75.0255953690465,"F11-17":117.22939062383,"F18-24":69.2761672281711,"F25-39":181.776636848553,"F40-54":253.685046816816,"F55-64":177.994631678694,"F65-79":211.819617471823,"F80+":109.228613770576,"H0-2":32.3977910345278,"H3-5":29.1721692944797,"H6-10":73.9106365748173,"H11-17":129.938673837891,"H18-24":99.0048691456923,"H25-39":217.933720343405,"H40-54":236.942025953619,"H55-64":197.8289706682,"H65-79":178.313896794431,"H80+":58.1695833216878},"Analyse":{"Votes décisifs":709,"tour décisif":1,"majeurs":1991.9737800416679,"Non votants de 18-24":65.46943146272454}}