{"id":5997,"slug":"59-654-waziers","nom_standard":"Waziers","code_postal":"59","code_departement":"59","libelle_departement":"Nord","code_commune":"654","Tour 1":{"Inscrits":4975,"Abstentions":2512,"% Abs/Ins":50.49,"Votants":2463,"% Vot/Ins":49.51,"Blancs":23,"% Blancs/Ins":0.46,"% Blancs/Vot":0.93,"Nuls":33,"% Nuls/Ins":0.66,"% Nuls/Vot":1.34,"Exprimés":2407,"% Exp/Ins":48.38,"% Exp/Vot":97.73,"resultats":[{"N.Pan.":null,"Code Nuance":"LCOM","Sexe":"M","Nom":"MICHON","Prénom":"Jacques","Liste":"AGIR POUR WAZIERS","Sièges / Elu":"0","Sièges Secteur":0,"Sièges CC":0,"Voix":823,"% Voix/Ins":16.54,"% Voix/Exp":34.19},{"N.Pan.":2,"Code Nuance":"LDVG","Sexe":"M","Nom":"DESMONS","Prénom":"Laurent","Liste":"VIA WAZIERS","Sièges / Elu":"0","Sièges Secteur":0,"Sièges CC":0,"Voix":881,"% Voix/Ins":17.71,"% Voix/Exp":36.6},{"N.Pan.":3,"Code Nuance":"LDVG","Sexe":"M","Nom":"BÄNSCH","Prénom":"Steve","Liste":"WAZIERS 2020, PLUS PROCHE DE VOUS !","Sièges / Elu":0,"Sièges CC":0,"Voix":703,"% Voix/Ins":14.13,"% Voix/Exp":29.21}]},"Tour 2":{"Inscrits":4987,"Abstentions":2301,"% Abs/Ins":46.14,"Votants":2686,"% Vot/Ins":53.86,"Blancs":24,"% Blancs/Ins":0.48,"% Blancs/Vot":0.89,"Nuls":35,"% Nuls/Ins":0.7,"% Nuls/Vot":1.3,"Exprimés":2627,"% Exp/Ins":52.68,"% Exp/Vot":97.8,"resultats":[{"N.Pan.":1,"Code Nuance":"LCOM","Sexe":"M","Nom":"MICHON","Prénom":"Jacques","Liste":"AGIR POUR WAZIERS","Sièges / Elu":6,"Sièges Secteur":0,"Sièges CC":1,"Voix":1113,"% Voix/Ins":22.32,"% Voix/Exp":42.37},{"N.Pan.":2,"Code Nuance":"LDVG","Sexe":"M","Nom":"DESMONS","Prénom":"Laurent","Liste":"VIA WAZIERS","Sièges / Elu":23,"Sièges Secteur":0,"Sièges CC":2,"Voix":1514,"% Voix/Ins":30.36,"% Voix/Exp":57.63}]},"population":{"F0-2":164.395036868161,"F3-5":166.276229469592,"F6-10":285.269495952244,"F11-17":399.100464024406,"F18-24":321.411605268424,"F25-39":675.604371905744,"F40-54":703.144998913983,"F55-64":478.88270519862,"F65-79":422.020996542167,"F80+":235.992481525051,"H0-2":149.446749035282,"H3-5":156.234701355661,"H6-10":304.232704429397,"H11-17":429.892509658417,"H18-24":333.001946731691,"H25-39":635.393795976307,"H40-54":622.034718598644,"H55-64":419.067089659451,"H65-79":358.476491951914,"H80+":121.120906934843},"Analyse":{"Votes décisifs":401,"tour décisif":2,"majeurs":5326.15210920684,"Non votants de 18-24":324.3901571305174}}