{"id":6140,"slug":"60-589-saint-maximin","nom_standard":"Saint-Maximin","code_postal":"60","code_departement":"60","libelle_departement":"Oise","code_commune":"589","Tour 1":{"Inscrits":1942,"Abstentions":1043,"% Abs/Ins":53.71,"Votants":899,"% Vot/Ins":46.29,"Blancs":7,"% Blancs/Ins":0.36,"% Blancs/Vot":0.78,"Nuls":11,"% Nuls/Ins":0.57,"% Nuls/Vot":1.22,"Exprimés":881,"% Exp/Ins":45.37,"% Exp/Vot":98,"resultats":[{"N.Pan.":null,"Code Nuance":"LNC","Sexe":"F","Nom":"BERGER","Prénom":"Séverine","Liste":"RENOUVEAU CITOYEN","Sièges / Elu":"4","Sièges Secteur":0,"Sièges CC":0,"Voix":329,"% Voix/Ins":16.94,"% Voix/Exp":37.34},{"N.Pan.":2,"Code Nuance":"LNC","Sexe":"M","Nom":"MACUDZINSKI","Prénom":"Serge","Liste":"\"Ecoute-Solidarité et protection de la nature\" NOS PRIORITES POUR SAINT MAXIMIN","Sièges / Elu":"19","Sièges Secteur":0,"Sièges CC":2,"Voix":552,"% Voix/Ins":28.42,"% Voix/Exp":62.66}]},"population":{"F0-2":57.2575613494447,"F3-5":57.0084003270622,"F6-10":116.588501486726,"F11-17":120.465709279731,"F18-24":88.0765862630624,"F25-39":316.272545263709,"F40-54":315.220866505264,"F55-64":202.600922711017,"F65-79":178.005543528897,"F80+":64.0312384273687,"H0-2":59.3398142972386,"H3-5":53.584427725112,"H6-10":122.55788525445,"H11-17":125.818719558985,"H18-24":97.1372542902066,"H25-39":287.945519451292,"H40-54":289.627905168116,"H55-64":173.525369356661,"H65-79":146.503298905299,"H80+":35.4319308503584},"Analyse":{"Votes décisifs":224,"tour décisif":1,"majeurs":2194.3789807212506,"Non votants de 18-24":109.33485879112094}}