{"id":6201,"slug":"61-230-longny-les-villages","nom_standard":"Longny-les-Villages","code_postal":"61","code_departement":"61","libelle_departement":"Orne","code_commune":"230","Tour 1":{"Inscrits":2337,"Abstentions":1061,"% Abs/Ins":45.4,"Votants":1276,"% Vot/Ins":54.6,"Blancs":20,"% Blancs/Ins":0.86,"% Blancs/Vot":1.57,"Nuls":26,"% Nuls/Ins":1.11,"% Nuls/Vot":2.04,"Exprimés":1230,"% Exp/Ins":52.63,"% Exp/Vot":96.39,"resultats":[{"N.Pan.":null,"Code Nuance":"LNC","Sexe":"M","Nom":"BAILLIF","Prénom":"Christian","Liste":"CONSTRUIRE ENSEMBLE POUR L'AVENIR","Sièges / Elu":"24","Sièges Secteur":0,"Sièges CC":9,"Voix":618,"% Voix/Ins":26.44,"% Voix/Exp":50.24},{"N.Pan.":2,"Code Nuance":"LNC","Sexe":"F","Nom":"ENCELIN","Prénom":"Elyane","Liste":"LONGNY LES VILLAGES UN AVENIR A PARTAGER","Sièges / Elu":"7","Sièges Secteur":0,"Sièges CC":2,"Voix":612,"% Voix/Ins":26.19,"% Voix/Exp":49.76}]},"population":{"F0-2":33.0843269451913,"F3-5":29.5031636007669,"F6-10":84.8380895930946,"F11-17":108.483103818714,"F18-24":47.9692445486397,"F25-39":190.386411336711,"F40-54":253.325897371409,"F55-64":244.529256387364,"F65-79":322.575676961375,"F80+":196.651252743018,"H0-2":33.574699489725,"H3-5":32.858034061747,"H6-10":66.5274722600433,"H11-17":115.91507099985,"H18-24":73.1438144839598,"H25-39":158.354651283133,"H40-54":243.297203443807,"H55-64":245.920371578306,"H65-79":318.878638013815,"H80+":130.18362107933},"Analyse":{"Votes décisifs":7,"tour décisif":1,"majeurs":2425.2160392308674,"Non votants de 18-24":57.39079230430925}}