{"id":6311,"slug":"62-268-desvres","nom_standard":"Desvres","code_postal":"62","code_departement":"62","libelle_departement":"Pas-de-Calais","code_commune":"268","Tour 1":{"Inscrits":3407,"Abstentions":1827,"% Abs/Ins":53.62,"Votants":1580,"% Vot/Ins":46.38,"Blancs":21,"% Blancs/Ins":0.62,"% Blancs/Vot":1.33,"Nuls":64,"% Nuls/Ins":1.88,"% Nuls/Vot":4.05,"Exprimés":1495,"% Exp/Ins":43.88,"% Exp/Vot":94.62,"resultats":[{"N.Pan.":null,"Code Nuance":"LDIV","Sexe":"M","Nom":"MARCOTTE","Prénom":"Jean-Luc","Liste":"Desvres autrement : un maire à plein-temps","Sièges / Elu":"5","Sièges Secteur":0,"Sièges CC":2,"Voix":574,"% Voix/Ins":16.85,"% Voix/Exp":38.39},{"N.Pan.":2,"Code Nuance":"LDVG","Sexe":"M","Nom":"DEMOLLIENS","Prénom":"Marc","Liste":"Agir pour Desvres continuons ensemble","Sièges / Elu":"22","Sièges Secteur":0,"Sièges CC":9,"Voix":921,"% Voix/Ins":27.03,"% Voix/Exp":61.61}]},"population":{"F0-2":91.39786004021,"F3-5":103.139381064919,"F6-10":133.75750616345,"F11-17":246.712745262451,"F18-24":189.02794141362,"F25-39":407.194649289969,"F40-54":451.638095341734,"F55-64":286.593185738332,"F65-79":390.194964670759,"F80+":254.035396063445,"H0-2":80.3449406725687,"H3-5":93.2362281197786,"H6-10":152.56078399164,"H11-17":238.749318039397,"H18-24":178.905428422813,"H25-39":389.463605565885,"H40-54":454.646535734956,"H55-64":277.360080833392,"H65-79":308.663285365726,"H80+":133.378068204955},"Analyse":{"Votes décisifs":348,"tour décisif":1,"majeurs":3721.101236645587,"Non votants de 18-24":211.706842426603}}