{"id":6318,"slug":"62-288-ecques","nom_standard":"Ecques","code_postal":"62","code_departement":"62","libelle_departement":"Pas-de-Calais","code_commune":"288","Tour 1":{"Inscrits":1671,"Abstentions":854,"% Abs/Ins":51.11,"Votants":817,"% Vot/Ins":48.89,"Blancs":22,"% Blancs/Ins":1.32,"% Blancs/Vot":2.69,"Nuls":163,"% Nuls/Ins":9.75,"% Nuls/Vot":19.95,"Exprimés":632,"% Exp/Ins":37.82,"% Exp/Vot":77.36,"resultats":[{"N.Pan.":null,"Code Nuance":"LNC","Sexe":"F","Nom":"MERCHIER","Prénom":"Brigitte","Liste":"Vivons ensemble notre village !","Sièges / Elu":"19","Sièges Secteur":0,"Sièges CC":1,"Voix":632,"% Voix/Ins":37.82,"% Voix/Exp":100}]},"population":{"F0-2":37,"F3-5":48,"F6-10":73,"F11-17":101,"F18-24":68,"F25-39":207,"F40-54":204,"F55-64":164,"F65-79":118,"F80+":92,"H0-2":40,"H3-5":38,"H6-10":80,"H11-17":106,"H18-24":63,"H25-39":180,"H40-54":231,"H55-64":167,"H65-79":115,"H80+":46},"Analyse":{"Votes décisifs":633,"tour décisif":1,"majeurs":1655,"Non votants de 18-24":66.33111782477341}}