{"id":7332,"slug":"69-277-genas","nom_standard":"Genas","code_postal":"69","code_departement":"69","libelle_departement":"Rhône","code_commune":"277","Tour 1":{"Inscrits":10398,"Abstentions":6025,"% Abs/Ins":57.94,"Votants":4373,"% Vot/Ins":42.06,"Blancs":27,"% Blancs/Ins":0.26,"% Blancs/Vot":0.62,"Nuls":40,"% Nuls/Ins":0.38,"% Nuls/Vot":0.91,"Exprimés":4306,"% Exp/Ins":41.41,"% Exp/Vot":98.47,"resultats":[{"N.Pan.":null,"Code Nuance":"LDVD","Sexe":"M","Nom":"VALÉRO","Prénom":"Daniel","Liste":"GENAS C'EST VOUS","Sièges / Elu":"29","Sièges Secteur":0,"Sièges CC":10,"Voix":2987,"% Voix/Ins":28.73,"% Voix/Exp":69.37},{"N.Pan.":2,"Code Nuance":"LDVC","Sexe":"F","Nom":"NOTIN","Prénom":"Stéphanie","Liste":"INSPIRE GENAS","Sièges / Elu":"2","Sièges Secteur":0,"Sièges CC":1,"Voix":673,"% Voix/Ins":6.47,"% Voix/Exp":15.63},{"N.Pan.":3,"Code Nuance":"LSOC","Sexe":"F","Nom":"BERGAME","Prénom":"Françoise","Liste":"GENAS ENSEMBLE","Sièges / Elu":2,"Sièges CC":1,"Voix":646,"% Voix/Ins":6.21,"% Voix/Exp":15}]},"population":{"F0-2":173.885965888047,"F3-5":206.547359992056,"F6-10":412.198200609149,"F11-17":657.098885953193,"F18-24":449.326548336792,"F25-39":1027.31958147421,"F40-54":1547.66556606349,"F55-64":933.537329014967,"F65-79":899.556274779813,"F80+":486.107593410954,"H0-2":199.073464537606,"H3-5":208.609086062932,"H6-10":478.063909377811,"H11-17":658.160576395199,"H18-24":500.356429027641,"H25-39":904.28737798455,"H40-54":1461.59930357937,"H55-64":930.906797581978,"H65-79":732.8004338676,"H80+":327.899316062646},"Analyse":{"Votes décisifs":1669,"tour décisif":1,"majeurs":10201.362551184011,"Non votants de 18-24":542.5840590407571}}