{"id":7562,"slug":"72-176-le-lude","nom_standard":"Le Lude","code_postal":"72","code_departement":"72","libelle_departement":"Sarthe","code_commune":"176","Tour 1":{"Inscrits":3369,"Abstentions":1992,"% Abs/Ins":59.13,"Votants":1377,"% Vot/Ins":40.87,"Blancs":33,"% Blancs/Ins":0.98,"% Blancs/Vot":2.4,"Nuls":70,"% Nuls/Ins":2.08,"% Nuls/Vot":5.08,"Exprimés":1274,"% Exp/Ins":37.82,"% Exp/Vot":92.52,"resultats":[{"N.Pan.":null,"Code Nuance":"LDVG","Sexe":"M","Nom":"FRIZON","Prénom":"Roland","Liste":"Le Lude Alternative","Sièges / Elu":"6","Sièges Secteur":0,"Sièges CC":1,"Voix":524,"% Voix/Ins":15.55,"% Voix/Exp":41.13},{"N.Pan.":2,"Code Nuance":"LDVD","Sexe":"F","Nom":"LATOUCHE","Prénom":"Beatrice","Liste":"AGIR ENSEMBLE POUR LA COMMUNE NOUVELLE","Sièges / Elu":"23","Sièges Secteur":0,"Sièges CC":6,"Voix":750,"% Voix/Ins":22.26,"% Voix/Exp":58.87}]},"population":{"F0-2":48.2735019733096,"F3-5":51.7509601583624,"F6-10":92.7823343246643,"F11-17":158.088597649723,"F18-24":82.6200876926296,"F25-39":224.860526135321,"F40-54":361.621575872156,"F55-64":352.889963589067,"F65-79":450.03682077668,"F80+":295.274521280131,"H0-2":47.5305494155888,"H3-5":54.9028519718368,"H6-10":101.280207468095,"H11-17":171.158497882857,"H18-24":93.0053703860247,"H25-39":231.301958006861,"H40-54":369.798933018991,"H55-64":311.956977341366,"H65-79":429.879005179021,"H80+":170.986759877314},"Analyse":{"Votes décisifs":227,"tour décisif":1,"majeurs":3374.2324991555624,"Non votants de 18-24":103.953972537919}}