{"id":7974,"slug":"76-366-le-houlme","nom_standard":"Le Houlme","code_postal":"76","code_departement":"76","libelle_departement":"Seine-Maritime","code_commune":"366","Tour 1":{"Inscrits":3065,"Abstentions":1964,"% Abs/Ins":64.08,"Votants":1101,"% Vot/Ins":35.92,"Blancs":23,"% Blancs/Ins":0.75,"% Blancs/Vot":2.09,"Nuls":16,"% Nuls/Ins":0.52,"% Nuls/Vot":1.45,"Exprimés":1062,"% Exp/Ins":34.65,"% Exp/Vot":96.46,"resultats":[{"N.Pan.":null,"Code Nuance":"LDVG","Sexe":"M","Nom":"GRENIER","Prénom":"Daniel","Liste":"LE HOULME DEMAIN","Sièges / Elu":"23","Sièges Secteur":0,"Sièges CC":1,"Voix":717,"% Voix/Ins":23.39,"% Voix/Exp":67.51},{"N.Pan.":2,"Code Nuance":"LDIV","Sexe":"M","Nom":"TURPAUD","Prénom":"Thierry","Liste":"LE HOULME ENSEMBLE","Sièges / Elu":"4","Sièges Secteur":0,"Sièges CC":0,"Voix":345,"% Voix/Ins":11.26,"% Voix/Exp":32.49}]},"population":{"F0-2":86.3692120443297,"F3-5":67.032915824875,"F6-10":100.207510114962,"F11-17":159.22014289644,"F18-24":169.695624202809,"F25-39":360.865016989404,"F40-54":417.47452820094,"F55-64":321.753569970976,"F65-79":327.55269703828,"F80+":201.034935547686,"H0-2":86.4569008407441,"H3-5":78.3957090295859,"H6-10":144.780909793283,"H11-17":168.256230567792,"H18-24":172.187601455362,"H25-39":336.793114745109,"H40-54":351.073186709361,"H55-64":246.403930430952,"H65-79":255.978696596224,"H80+":97.4675670008845},"Analyse":{"Votes décisifs":373,"tour décisif":1,"majeurs":3258.280468887988,"Non votants de 18-24":226.35804756381512}}