{"id":8447,"slug":"78-688-voisins-le-bretonneux","nom_standard":"Voisins-le-Bretonneux","code_postal":"78","code_departement":"78","libelle_departement":"Yvelines","code_commune":"688","Tour 1":{"Inscrits":8972,"Abstentions":4750,"% Abs/Ins":52.94,"Votants":4222,"% Vot/Ins":47.06,"Blancs":30,"% Blancs/Ins":0.33,"% Blancs/Vot":0.71,"Nuls":70,"% Nuls/Ins":0.78,"% Nuls/Vot":1.66,"Exprimés":4122,"% Exp/Ins":45.94,"% Exp/Vot":97.63,"resultats":[{"N.Pan.":null,"Code Nuance":"LDVC","Sexe":"F","Nom":"ROSETTI","Prénom":"Alexandra","Liste":"ALEXANDRA ROSETTI 2020","Sièges / Elu":"0","Sièges Secteur":0,"Sièges CC":0,"Voix":1967,"% Voix/Ins":21.92,"% Voix/Exp":47.72},{"N.Pan.":2,"Code Nuance":"LDVD","Sexe":"M","Nom":"AFONSO","Prénom":"Olivier","Liste":"UNIS POUR VOISINS","Sièges / Elu":"0","Sièges Secteur":0,"Sièges CC":0,"Voix":1437,"% Voix/Ins":16.02,"% Voix/Exp":34.86},{"N.Pan.":3,"Code Nuance":"LDVG","Sexe":"F","Nom":"PIERRAT","Prénom":"Béatrice","Liste":"Avec vous Voisins avance","Sièges / Elu":0,"Sièges CC":0,"Voix":718,"% Voix/Ins":8,"% Voix/Exp":17.42}]},"Tour 2":{"Inscrits":9005,"Abstentions":4988,"% Abs/Ins":55.39,"Votants":4017,"% Vot/Ins":44.61,"Blancs":49,"% Blancs/Ins":0.54,"% Blancs/Vot":1.22,"Nuls":38,"% Nuls/Ins":0.42,"% Nuls/Vot":0.95,"Exprimés":3930,"% Exp/Ins":43.64,"% Exp/Vot":97.83,"resultats":[{"N.Pan.":1,"Code Nuance":"LDVC","Sexe":"F","Nom":"ROSETTI","Prénom":"Alexandra","Liste":"ALEXANDRA ROSETTI 2020","Sièges / Elu":26,"Sièges Secteur":0,"Sièges CC":3,"Voix":2087,"% Voix/Ins":23.18,"% Voix/Exp":53.1},{"N.Pan.":2,"Code Nuance":"LDVD","Sexe":"M","Nom":"AFONSO","Prénom":"Olivier","Liste":"UNIS POUR VOISINS","Sièges / Elu":5,"Sièges Secteur":0,"Sièges CC":1,"Voix":1215,"% Voix/Ins":13.49,"% Voix/Exp":30.92},{"N.Pan.":3,"Code Nuance":"LDVG","Sexe":"F","Nom":"PIERRAT","Prénom":"Béatrice","Liste":"Avec vous Voisins avance","Sièges / Elu":2,"Sièges Secteur":0,"Sièges CC":0,"Voix":628,"% Voix/Ins":6.97,"% Voix/Exp":15.98}]},"population":{"F0-2":134.060796151336,"F3-5":180.681774439525,"F6-10":343.702354820529,"F11-17":511.00087791682,"F18-24":423.45157502217,"F25-39":852.148863322803,"F40-54":1241.55225376108,"F55-64":801.851845023526,"F65-79":757.549679224071,"F80+":212.657971424452,"H0-2":132.970222033676,"H3-5":160.226794769271,"H6-10":384.622195421395,"H11-17":572.939995608257,"H18-24":446.924426730477,"H25-39":873.21701182258,"H40-54":1167.70576066981,"H55-64":714.944516491455,"H65-79":690.740215559771,"H80+":119.050869786994},"Analyse":{"Votes décisifs":872,"tour décisif":2,"majeurs":8301.794988839189,"Non votants de 18-24":449.2260692692795}}