{"id":8540,"slug":"80-39-ault","nom_standard":"Ault","code_postal":"80","code_departement":"80","libelle_departement":"Somme","code_commune":"39","Tour 1":{"Inscrits":1353,"Abstentions":395,"% Abs/Ins":29.19,"Votants":958,"% Vot/Ins":70.81,"Blancs":9,"% Blancs/Ins":0.67,"% Blancs/Vot":0.94,"Nuls":19,"% Nuls/Ins":1.4,"% Nuls/Vot":1.98,"Exprimés":930,"% Exp/Ins":68.74,"% Exp/Vot":97.08,"resultats":[{"N.Pan.":null,"Code Nuance":"LNC","Sexe":"M","Nom":"LE MOIGNE","Prénom":"Marcel","Liste":"UN AUTRE REGARD SUR AULT","Sièges / Elu":"13","Sièges Secteur":0,"Sièges CC":2,"Voix":669,"% Voix/Ins":49.45,"% Voix/Exp":71.94},{"N.Pan.":2,"Code Nuance":"LNC","Sexe":"M","Nom":"RICHARD","Prénom":"Patrick","Liste":"Agir ensemble pour Ault","Sièges / Elu":"2","Sièges Secteur":0,"Sièges CC":0,"Voix":261,"% Voix/Ins":19.29,"% Voix/Exp":28.06}]},"population":{"F0-2":13.5773235244215,"F3-5":19.2697174917114,"F6-10":14.5497811298286,"F11-17":38.7395241658586,"F18-24":36.3295163595263,"F25-39":70.3738356013384,"F40-54":118.385124863574,"F55-64":115.772063453238,"F65-79":205.137959864086,"F80+":76.3324361073178,"H0-2":17.4395406771418,"H3-5":19.3081768817862,"H6-10":31.1290436629236,"H11-17":41.8049832115738,"H18-24":43.0268396206444,"H25-39":74.7804779585984,"H40-54":111.600684991023,"H55-64":125.601780057123,"H65-79":160.812633791374,"H80+":49.0285565869114},"Analyse":{"Votes décisifs":409,"tour décisif":1,"majeurs":1187.1819092547548,"Non votants de 18-24":15.319506668065971}}