{"id":8637,"slug":"81-48-cagnac-les-mines","nom_standard":"Cagnac-les-Mines","code_postal":"81","code_departement":"81","libelle_departement":"Tarn","code_commune":"48","Tour 1":{"Inscrits":1930,"Abstentions":718,"% Abs/Ins":37.2,"Votants":1212,"% Vot/Ins":62.8,"Blancs":1,"% Blancs/Ins":0.05,"% Blancs/Vot":0.08,"Nuls":28,"% Nuls/Ins":1.45,"% Nuls/Vot":2.31,"Exprimés":1183,"% Exp/Ins":61.3,"% Exp/Vot":97.61,"resultats":[{"N.Pan.":null,"Code Nuance":"LNC","Sexe":"M","Nom":"NORKOWSKI","Prénom":"Patrice","Liste":"CAGNAC PARTAGEONS DEMAIN","Sièges / Elu":"18","Sièges Secteur":0,"Sièges CC":3,"Voix":635,"% Voix/Ins":32.9,"% Voix/Exp":53.68},{"N.Pan.":2,"Code Nuance":"LNC","Sexe":"M","Nom":"ASTORG","Prénom":"Philippe","Liste":"ECOUTER, S'UNIR, AGIR POUR CAGNAC","Sièges / Elu":"5","Sièges Secteur":0,"Sièges CC":1,"Voix":548,"% Voix/Ins":28.39,"% Voix/Exp":46.32}]},"population":{"F0-2":56.45608356194,"F3-5":41.6535549222771,"F6-10":79.4815615339468,"F11-17":80.7162309557497,"F18-24":57.5205894579218,"F25-39":245.320161569438,"F40-54":253.636239873662,"F55-64":181.968761564476,"F65-79":227.94842689243,"F80+":121.665667880355,"H0-2":44.9644994729554,"H3-5":40.838541102838,"H6-10":81.6960312330151,"H11-17":90.4291436582833,"H18-24":65.1410702302415,"H25-39":220.683139892326,"H40-54":269.103928601533,"H55-64":165.581755728122,"H65-79":192.881736997489,"H80+":62.3128748709992},"Analyse":{"Votes décisifs":88,"tour décisif":1,"majeurs":2063.7643535589937,"Non votants de 18-24":50.62536771244562}}