{"id":8915,"slug":"84-68-lourmarin","nom_standard":"Lourmarin","code_postal":"84","code_departement":"84","libelle_departement":"Vaucluse","code_commune":"68","Tour 1":{"Inscrits":1081,"Abstentions":337,"% Abs/Ins":31.17,"Votants":744,"% Vot/Ins":68.83,"Blancs":4,"% Blancs/Ins":0.37,"% Blancs/Vot":0.54,"Nuls":5,"% Nuls/Ins":0.46,"% Nuls/Vot":0.67,"Exprimés":735,"% Exp/Ins":67.99,"% Exp/Vot":98.79,"resultats":[{"N.Pan.":null,"Code Nuance":"LNC","Sexe":"M","Nom":"PETTAVINO","Prénom":"Jean-Pierre","Liste":"LOURMARIN POUR VOUS AVEC VOUS","Sièges / Elu":"12","Sièges Secteur":0,"Sièges CC":1,"Voix":426,"% Voix/Ins":39.41,"% Voix/Exp":57.96},{"N.Pan.":2,"Code Nuance":"LNC","Sexe":"M","Nom":"VOLLAIRE","Prénom":"Olivier","Liste":"ENSEMBLE POUR LOURMARIN","Sièges / Elu":"3","Sièges Secteur":0,"Sièges CC":0,"Voix":309,"% Voix/Ins":28.58,"% Voix/Exp":42.04}]},"population":{"F0-2":9.85273848043536,"F3-5":14.5604909321638,"F6-10":19.2956004210345,"F11-17":39.833449537527,"F18-24":14.8013382874681,"F25-39":66.2229902791309,"F40-54":114.971891634036,"F55-64":94.8705388349771,"F65-79":128.409744502273,"F80+":70.4547741042967,"H0-2":7.82788539039431,"H3-5":9.70292126878358,"H6-10":22.1104022067597,"H11-17":37.0643529117878,"H18-24":20.7160575608707,"H25-39":62.9223399097439,"H40-54":93.234347221235,"H55-64":84.5135080078822,"H65-79":90.059804452326,"H80+":40.5748240568753},"Analyse":{"Votes décisifs":118,"tour décisif":1,"majeurs":881.7521588511149,"Non votants de 18-24":5.548722399787645}}